aarya/__init__.py
aarya/cli.py
aarya/setup.py
aarya/modules/__init__.py
aarya/modules/funding/__init__.py
aarya/modules/learning/duolingo.py
aarya/modules/mail/gmail.py
aarya/modules/mail/proton.py
aarya/modules/music/spotify.py
aarya/modules/shopping/amazon.py
aarya/modules/shopping/flipkart.py
aarya/modules/social/instagram.py
aarya/modules/social/twitter.py
aarya/modules/social/wattpad.py
aarya/shared/utils.py
aarya-1.0.9.dist-info/licenses/LICENSE
aarya-1.0.9.dist-info/METADATA
aarya-1.0.9.dist-info/WHEEL
aarya-1.0.9.dist-info/entry_points.txt
aarya-1.0.9.dist-info/top_level.txt
aarya-1.0.9.dist-info/RECORD
