Metadata-Version: 2.4
Name: aarya
Version: 1.0.9
Summary: Validates the existence of registered accounts across social & shopping platforms and extracts rich identity intelligence (Names, Photos, IDs).
Author-email: Shaurya Mishra <shaur.codes@gmail.com>
License:                     GNU GENERAL PUBLIC LICENSE
Project-URL: Homepage, https://github.com/forshaur/aarya
Project-URL: Bug Tracker, https://github.com/forshaur/aarya/issues
Classifier: Programming Language :: Python :: 3
Classifier: License :: OSI Approved :: GNU General Public License v3 (GPLv3)
Classifier: Operating System :: OS Independent
Classifier: Topic :: Security
Classifier: Topic :: Utilities
Classifier: Intended Audience :: Information Technology
Requires-Python: >=3.8
License-File: LICENSE
Requires-Dist: httpx
Requires-Dist: requests
Requires-Dist: beautifulsoup4
Requires-Dist: browser_cookie3
Requires-Dist: rich
Dynamic: license-file
